{
    "data": [
        {
            "項目": "福利品04",
            "SKU": "福利品04",
            "銷售額": 1200.0,
            "數量": 15
        },
        {
            "項目": "卡套+掛繩",
            "SKU": "006",
            "銷售額": 450.0,
            "數量": 3
        },
        {
            "項目": "福利品03",
            "SKU": "福利品03",
            "銷售額": 770.0,
            "數量": 11
        },
        {
            "項目": "動物園",
            "SKU": "006",
            "銷售額": 2040.0,
            "數量": 17
        },
        {
            "項目": "徽章盲包",
            "SKU": "006",
            "銷售額": 360.0,
            "數量": 3
        },
        {
            "項目": "迷你動物園吊飾",
            "SKU": "暖羊",
            "銷售額": 990.0,
            "數量": 11
        },
        {
            "項目": "福利品02吊飾",
            "SKU": "暖羊",
            "銷售額": 420.0,
            "數量": 7
        },
        {
            "項目": "吊飾",
            "SKU": "暖羊",
            "銷售額": 2400.0,
            "數量": 20
        },
        {
            "項目": "針織袋",
            "SKU": "暖羊",
            "銷售額": 470.0,
            "數量": 1
        },
        {
            "項目": "御守吊飾盲包",
            "SKU": "暖羊",
            "銷售額": 480.0,
            "數量": 4
        },
        {
            "項目": "冰淇淋吊飾盲包",
            "SKU": "暖羊",
            "銷售額": 360.0,
            "數量": 3
        },
        {
            "項目": "磁吸支架",
            "SKU": "暖羊",
            "銷售額": 1050.0,
            "數量": 3
        },
        {
            "項目": "刨冰吊飾盲包",
            "SKU": "暖羊",
            "銷售額": 360.0,
            "數量": 3
        },
        {
            "項目": "台灣羊酒吊飾",
            "SKU": "暖羊",
            "銷售額": 600.0,
            "數量": 5
        },
        {
            "項目": "冰淇淋餅乾吊飾盲包",
            "SKU": "暖羊",
            "銷售額": 1440.0,
            "數量": 12
        },
        {
            "項目": "暖羊動物園明信片",
            "SKU": "暖羊",
            "銷售額": 35.0,
            "數量": 1
        },
        {
            "項目": "卡套",
            "SKU": "暖羊",
            "銷售額": 100.0,
            "數量": 1
        },
        {
            "項目": "貼紙B款",
            "SKU": "暖羊",
            "銷售額": 80.0,
            "數量": 4
        },
        {
            "項目": "御守香氛",
            "SKU": "暖羊",
            "銷售額": 100.0,
            "數量": 1
        },
        {
            "項目": "打火機組合",
            "SKU": "暖羊",
            "銷售額": 300.0,
            "數量": 2
        },
        {
            "項目": "暖羊冰品明信片",
            "SKU": "暖羊",
            "銷售額": 35.0,
            "數量": 1
        }
    ],
    "total_sales": 14040.0,
    "total_quantity": 128,
    "commission_rate": 10.0,
    "commission": 1404.0,
    "net_amount": 12636.0
}